easyprotocol/__init__.py
easyprotocol/easyprotocol.py
easyprotocol/test_easy_protocol.py
one_easy_protocol-0.4.dist-info/LICENCE.txt
one_easy_protocol-0.4.dist-info/LICENSE
one_easy_protocol-0.4.dist-info/METADATA
one_easy_protocol-0.4.dist-info/WHEEL
one_easy_protocol-0.4.dist-info/top_level.txt
one_easy_protocol-0.4.dist-info/RECORD
