Metadata-Version: 2.1
Name: one-easy-protocol
Version: 0.4
Summary: Easy protocol for serial communication between a Device and Delta-Robot One
Home-page: https://github.com/deltarobotone
Author: Delta-Robot One
Author-email: deltarobotone@web.de
License: LGPLv3+
Download-URL: https://github.com/deltarobotone/one-easy-protocol/archive/v0.4.tar.gz
Platform: UNKNOWN
Classifier: Development Status :: 3 - Alpha
Classifier: Intended Audience :: Developers
Classifier: Intended Audience :: Education
Classifier: Topic :: Communications
Classifier: License :: OSI Approved :: GNU Lesser General Public License v3 or later (LGPLv3+)
Classifier: Programming Language :: Python :: 2.7
Classifier: Programming Language :: Python :: 3
Classifier: Programming Language :: Python :: 3.2
Classifier: Programming Language :: Python :: 3.3
Classifier: Programming Language :: Python :: 3.4
Classifier: Programming Language :: Python :: 3.5
Classifier: Programming Language :: Python :: 3.6
Classifier: Programming Language :: Python :: 3.7
Classifier: Programming Language :: Python :: 3.8
Requires-Dist: pyserial
